ytube_api/__init__.py
ytube_api/__main__.py
ytube_api/console.py
ytube_api/constants.py
ytube_api/exceptions.py
ytube_api/main.py
ytube_api/models.py
ytube_api/utils.py
ytube_api-0.1.2.dist-info/licenses/LICENSE
ytube_api-0.1.2.dist-info/METADATA
ytube_api-0.1.2.dist-info/WHEEL
ytube_api-0.1.2.dist-info/entry_points.txt
ytube_api-0.1.2.dist-info/top_level.txt
ytube_api-0.1.2.dist-info/RECORD
