Metadata-Version: 2.4
Name: ytube-api
Version: 0.1.2
Summary: Unofficial wrapper for y2mate.tube
Home-page: https://github.com/Simatwa/ytube-api
Author: Smartwa
Author-email: simatwacaleb@proton.me
Maintainer: Smartwa
License: MIT
Project-URL: Bug Report, https://github.com/Simatwa/ytube-api/issues/new
Project-URL: Homepage, https://github.com/Simatwa/ytube-api
Project-URL: Source Code, https://github.com/Simatwa/ytube-api
Project-URL: Issue Tracker, https://github.com/Simatwa/ytube-api/issues
Project-URL: Download, https://github.com/Simatwa/ytube-api/releases
Project-URL: Documentation, https://github.com/Simatwa/ytube-api/
Keywords: ytube,ytube-api,y2mate,y2mate-api,youtube,ytdlp,youtube-video-downloader
Classifier: License :: OSI Approved :: MIT License
Classifier: Intended Audience :: Developers
Classifier: Natural Language :: English
Classifier: License :: Free For Home Use
Classifier: Intended Audience :: Customer Service
Classifier: Programming Language :: Python
Classifier: Topic :: Software Development :: Libraries :: Python Modules
Classifier: Programming Language :: Python :: 3 :: Only
Classifier: Programming Language :: Python :: 3.9
Classifier: Programming Language :: Python :: 3.10
Classifier: Programming Language :: Python :: 3.11
Classifier: Programming Language :: Python :: 3.12
Classifier: Programming Language :: Python :: 3.13
Requires-Python: >=3.9
License-File: LICENSE
Requires-Dist: cloudscraper>=1.2.71
Requires-Dist: tqdm==4.66.3
Provides-Extra: cli
Requires-Dist: click==8.1.3; extra == "cli"
Requires-Dist: rich==13.9.2; extra == "cli"
Requires-Dist: prompt-toolkit==3.0.48; extra == "cli"
Requires-Dist: colorama==0.4.6; extra == "cli"
Provides-Extra: all
Requires-Dist: click==8.1.3; extra == "all"
Requires-Dist: rich==13.9.2; extra == "all"
Requires-Dist: prompt-toolkit==3.0.48; extra == "all"
Requires-Dist: colorama==0.4.6; extra == "all"
Dynamic: author
Dynamic: author-email
Dynamic: classifier
Dynamic: description
Dynamic: description-content-type
Dynamic: home-page
Dynamic: keywords
Dynamic: license
Dynamic: license-file
Dynamic: maintainer
Dynamic: project-url
Dynamic: provides-extra
Dynamic: requires-dist
Dynamic: requires-python
Dynamic: summary
